tinytim/__init__.py
tinytim/columns.py
tinytim/copy.py
tinytim/custom_types.py
tinytim/data.py
tinytim/dropna.py
tinytim/edit.py
tinytim/fillna.py
tinytim/filter.py
tinytim/group.py
tinytim/insert.py
tinytim/interfaces.py
tinytim/isna.py
tinytim/join.py
tinytim/json.py
tinytim/na.py
tinytim/py.typed
tinytim/rows.py
tinytim/sequences.py
tinytim/utils.py
tinytim/validate.py
tinytim/docs/conf.py
tinytim-1.12.0.dist-info/LICENSE.md
tinytim-1.12.0.dist-info/METADATA
tinytim-1.12.0.dist-info/WHEEL
tinytim-1.12.0.dist-info/top_level.txt
tinytim-1.12.0.dist-info/RECORD
