Metadata-Version: 2.1
Name: tinytim
Version: 1.12.0
Summary: Pure Python data table functions.
Author-email: Odos Matthews <odosmatthews@gmail.com>
License: MIT
Project-URL: Homepage, https://github.com/eddiethedean/tinytim
Project-URL: Repository, https://github.com/eddiethedean/tinytim
Project-URL: Issues, https://github.com/eddiethedean/tinytim/issues
Keywords: data,table,dataframe,pure-python,lightweight
Classifier: Development Status :: 5 - Production/Stable
Classifier: Intended Audience :: Developers
Classifier: License :: OSI Approved :: MIT License
Classifier: Programming Language :: Python :: 3
Classifier: Programming Language :: Python :: 3 :: Only
Classifier: Programming Language :: Python :: 3.8
Classifier: Programming Language :: Python :: 3.9
Classifier: Programming Language :: Python :: 3.10
Classifier: Programming Language :: Python :: 3.11
Classifier: Programming Language :: Python :: 3.12
Classifier: Topic :: Software Development :: Libraries :: Python Modules
Requires-Python: >=3.8
License-File: LICENSE.md
Requires-Dist: hasattrs>=0.0.2
Provides-Extra: dev
Requires-Dist: pytest>=8.3.0; extra == "dev"
Requires-Dist: pytest-cov>=5.0.0; extra == "dev"
Requires-Dist: mypy>=1.11.0; extra == "dev"
Requires-Dist: ruff>=0.6.0; extra == "dev"
Requires-Dist: tox>=4.0.0; extra == "dev"
